yeonjae_universal_git_data_parser/__init__.py
yeonjae_universal_git_data_parser/exceptions.py
yeonjae_universal_git_data_parser/models.py
yeonjae_universal_git_data_parser/py.typed
yeonjae_universal_git_data_parser/service.py
yeonjae_universal_git_data_parser-1.0.5.dist-info/METADATA
yeonjae_universal_git_data_parser-1.0.5.dist-info/WHEEL
yeonjae_universal_git_data_parser-1.0.5.dist-info/top_level.txt
yeonjae_universal_git_data_parser-1.0.5.dist-info/RECORD
