Metadata-Version: 2.4
Name: yeonjae-universal-git-data-parser
Version: 1.0.5
Summary: Universal Git webhook data parser supporting GitHub, GitLab, and other SCM platforms
Author-email: "CodePing.AI Team" <contact@codeping.ai>
License: MIT
Project-URL: Homepage, https://github.com/yeonjae-work/universal-modules
Project-URL: Repository, https://github.com/yeonjae-work/universal-modules
Project-URL: Issues, https://github.com/yeonjae-work/universal-modules/issues
Project-URL: Changelog, https://github.com/yeonjae-work/universal-modules/blob/main/packages/yeonjae-universal-git-data-parser/CHANGELOG.md
Keywords: git,github,gitlab,webhook,parser,scm,data-parsing,validation
Classifier: Development Status :: 5 - Production/Stable
Classifier: Intended Audience :: Developers
Classifier: License :: OSI Approved :: MIT License
Classifier: Operating System :: OS Independent
Classifier: Programming Language :: Python :: 3
Classifier: Programming Language :: Python :: 3.8
Classifier: Programming Language :: Python :: 3.9
Classifier: Programming Language :: Python :: 3.10
Classifier: Programming Language :: Python :: 3.11
Classifier: Programming Language :: Python :: 3.12
Classifier: Topic :: Software Development :: Libraries :: Python Modules
Classifier: Topic :: Software Development :: Version Control :: Git
Classifier: Topic :: Internet :: WWW/HTTP :: Dynamic Content
Classifier: Topic :: System :: Software Distribution
Requires-Python: >=3.8
Requires-Dist: pydantic>=2.0.0
Requires-Dist: typing-extensions>=4.0.0; python_version < "3.10"
Requires-Dist: requests>=2.28.0
Provides-Extra: github
Requires-Dist: pygithub>=1.58.0; extra == "github"
Provides-Extra: gitlab
Requires-Dist: python-gitlab>=3.15.0; extra == "gitlab"
Provides-Extra: validation
Requires-Dist: jsonschema>=4.17.0; extra == "validation"
Provides-Extra: all
Requires-Dist: pygithub>=1.58.0; extra == "all"
Requires-Dist: python-gitlab>=3.15.0; extra == "all"
Requires-Dist: jsonschema>=4.17.0; extra == "all"
Provides-Extra: dev
Requires-Dist: pytest>=7.0.0; extra == "dev"
Requires-Dist: pytest-asyncio>=0.21.0; extra == "dev"
Requires-Dist: pytest-mock>=3.10.0; extra == "dev"
Requires-Dist: black>=23.0.0; extra == "dev"
Requires-Dist: isort>=5.12.0; extra == "dev"
Requires-Dist: flake8>=6.0.0; extra == "dev"
Requires-Dist: mypy>=1.0.0; extra == "dev"
Requires-Dist: responses>=0.23.0; extra == "dev"
